epevermodbus/__init__.py
epevermodbus/command_line.py
epevermodbus/driver.py
epevermodbus/extract_bits.py
epevermodbus-0.0.16.dist-info/LICENSE
epevermodbus-0.0.16.dist-info/METADATA
epevermodbus-0.0.16.dist-info/WHEEL
epevermodbus-0.0.16.dist-info/entry_points.txt
epevermodbus-0.0.16.dist-info/top_level.txt
epevermodbus-0.0.16.dist-info/RECORD
