Metadata-Version: 2.1
Name: epevermodbus
Version: 0.0.16
Home-page: https://github.com/rosswarren/epevermodbus
Author: Ross Warren
Author-email: rosswarren4@gmail.com
License: MIT
Classifier: License :: OSI Approved :: MIT License
Classifier: Programming Language :: Python :: 3
License-File: LICENSE
Requires-Dist: minimalmodbus
Requires-Dist: retrying
